services_reviews/__init__.py
services_reviews/common_cli.py
services_reviews/client_data_aggregator/__init__.py
services_reviews/common_api/__init__.py
services_reviews/common_api/Api/__init__.py
services_reviews/common_api/Api/auth_controller/__init__.py
services_reviews/common_api/Api/auth_controller/auth_resources.py
services_reviews/common_api/Api/auth_controller/crud.py
services_reviews/common_api/Api/auth_controller/dataclases.py
services_reviews/common_api/Api/common_controller/__init__.py
services_reviews/common_api/Api/common_controller/system_resources.py
services_reviews/common_api/Api/common_controller/form_controller/__init__.py
services_reviews/common_api/Api/common_controller/form_controller/dataclasses.py
services_reviews/common_api/Api/common_controller/form_controller/form_render_resources.py
services_reviews/common_api/Api/common_controller/form_controller/form_resources.py
services_reviews/common_api/Api/common_controller/mailing_controller/__init__.py
services_reviews/common_api/Api/common_controller/mailing_controller/dataclasses.py
services_reviews/common_api/Api/common_controller/mailing_controller/mailing_resources.py
services_reviews/common_api/Api/exceptions/__init__.py
services_reviews/common_api/Api/exceptions/common.py
services_reviews/common_api/Api/exceptions/exception_handler.py
services_reviews/common_api/Api/routines/__init__.py
services_reviews/common_api/Api/routines/common.py
services_reviews/common_api/Api/routines/dataclasses.py
services_reviews/common_configs/__init__.py
services_reviews/common_configs/schema_common_api_conf.py
services_reviews/common_configs/schema_db_conf.py
services_reviews/common_configs/schema_ext_platform_conf.py
services_reviews/common_configs/schema_message_sender_conf.py
services_reviews/common_utils/__init__.py
services_reviews/common_utils/db_connect.py
services_reviews/common_utils/fetch.py
services_reviews/common_utils/read_conf.py
services_reviews/models/__init__.py
services_reviews-1.0.5.dist-info/LICENSE
services_reviews-1.0.5.dist-info/METADATA
services_reviews-1.0.5.dist-info/WHEEL
services_reviews-1.0.5.dist-info/entry_points.txt
services_reviews-1.0.5.dist-info/top_level.txt
services_reviews-1.0.5.dist-info/RECORD
